{
  "userPayouts": [
    {
      "userId": "USER_001",
      "payouts": [
        {
          "id": "RP-000010",
          "date": "2025-08-12",
          "grossEarnings": "$1,550.00",
          "fees": "$20.00",
          "tax": "$10.00",
          "wht": "$310.00",
          "netPayout": "$1,240.00"
        },
        {
          "id": "RP-000009", 
          "date": "2025-07-12",
          "grossEarnings": "$1,350.00",
          "fees": "$15.00",
          "tax": "$5.00",
          "wht": "$270.00", 
          "netPayout": "$1,080.00"
        },
        {
          "id": "RP-000008", 
          "date": "2025-06-12",
          "grossEarnings": "$820.00",
          "fees": "$20.00",
          "tax": "$10.00",
          "wht": "$164.00", 
          "netPayout": "$656.00"
        },
        {
          "id": "RP-000007", 
          "date": "2025-05-12",
          "grossEarnings": "$1,180.00",
          "fees": "$20.00",
          "tax": "$10.00",
          "wht": "$236.00", 
          "netPayout": "$944.00"
        },
        {
          "id": "RP-000006", 
          "date": "2025-04-12",
          "grossEarnings": "$620.00",
          "fees": "$20.00",
          "tax": "$10.00",
          "wht": "$124.00", 
          "netPayout": "$496.00"
        },
        {
          "id": "RP-000005", 
          "date": "2025-03-12",
          "grossEarnings": "$1,580.00",
          "fees": "$20.00",
          "tax": "$10.00",
          "wht": "$316.00", 
          "netPayout": "$1,264.00"
        },
        {
          "id": "RP-000004", 
          "date": "2025-02-12",
          "grossEarnings": "$950.00",
          "fees": "$20.00",
          "tax": "$10.00",
          "wht": "$190.00", 
          "netPayout": "$760.00"
        }
      ]
    },
    {
      "userId": "USER_002",
      "payouts": [
        {
          "id": "RP-000020",
          "date": "2025-08-05",
          "grossEarnings": "$3,100.00",
          "fees": "$25.00", 
          "tax": "$15.00",
          "wht": "$620.00",
          "netPayout": "$2,480.00"
        },
        {
          "id": "RP-000019",
          "date": "2025-07-05",
          "grossEarnings": "$2,750.00",
          "fees": "$22.00", 
          "tax": "$13.00",
          "wht": "$550.00",
          "netPayout": "$2,200.00"
        },
        {
          "id": "RP-000018",
          "date": "2025-06-05",
          "grossEarnings": "$2,450.00",
          "fees": "$20.00", 
          "tax": "$10.00",
          "wht": "$490.00",
          "netPayout": "$1,960.00"
        },
        {
          "id": "RP-000017",
          "date": "2025-05-05",
          "grossEarnings": "$2,200.00",
          "fees": "$18.00", 
          "tax": "$12.00",
          "wht": "$440.00",
          "netPayout": "$1,760.00"
        },
        {
          "id": "RP-000016",
          "date": "2025-04-05",
          "grossEarnings": "$1,950.00",
          "fees": "$15.00", 
          "tax": "$10.00",
          "wht": "$390.00",
          "netPayout": "$1,560.00"
        }
      ]
    }
  ]
}
